nonebot_plugin_llm_extension/__init__.py
nonebot_plugin_llm_extension/_client.py
nonebot_plugin_llm_extension/bootstrap.py
nonebot_plugin_llm_extension/config.py
nonebot_plugin_llm_extension/extension.py
nonebot_plugin_llm_extension-0.1.1.dist-info/WHEEL
nonebot_plugin_llm_extension-0.1.1.dist-info/METADATA
nonebot_plugin_llm_extension-0.1.1.dist-info/RECORD
