Metadata-Version: 2.3
Name: nonebot-plugin-llm-extension
Version: 0.1.1
Summary: 利用 LLM 将自然语言转换为机器人指令 / Convert natural language messages into bot commands using LLMs
Keywords: nonebot
Author: KomoriDev
Author-email: KomoriDev <mute231010@gmail.com>
License: MIT
Requires-Dist: nonebot-plugin-alconna>=0.59.4
Requires-Dist: nonebot2>=2.4.3
Requires-Python: >=3.10
Project-URL: homepage, https://github.com/KomoriDev/nonebot-plugin-llm-extension
Project-URL: repository, https://github.com/KomoriDev/nonebot-plugin-llm-extension
